i18n/Code_i18n_LibraryParser_parser.py
i18n/__init__.py
i18n/self_util.py
i18n/listeners/I18nListener.py
i18n/listeners/I18nMap.py
i18n/listeners/I18nTrigger.py
i18n/listeners/ManyTranslations.py
i18n/listeners/MappingRoutesGenerator.py
i18n/listeners/__init__.py
i18n/listeners/languageFiles/de-CH/common-de-CH.json
i18n/listeners/languageFiles/de-CH/more-de-CH.json
i18n/listeners/languageFiles/de-CH/office-de-CH.json
i18n/listeners/languageFiles/de-CH/support-de-CH.json
i18n/listeners/languageFiles/en-US/common-en-US.json
i18n/listeners/languageFiles/en-US/more-en-US.json
i18n/listeners/languageFiles/en-US/office-en-US.json
i18n/listeners/languageFiles/en-US/support-en-US.json
i18n/listeners/languageFiles/ja/common-ja.json
i18n/listeners/languageFiles/ja/more-ja.json
i18n/listeners/languageFiles/ja/office-ja.json
i18n/listeners/languageFiles/ja/support-ja.json
i18n/listeners/languageFiles/ko/common-ko.json
i18n/listeners/languageFiles/ko/more-ko.json
i18n/listeners/languageFiles/ko/office-ko.json
i18n/listeners/languageFiles/ko/support-ko.json
i18n/listeners/languageFiles/zh-CN/common-zh-CN.json
i18n/listeners/languageFiles/zh-CN/more-zh-CN.json
i18n/listeners/languageFiles/zh-CN/office-zh-CN.json
i18n/listeners/languageFiles/zh-CN/support-zh-CN.json
i18n/listeners/languageFiles/zh-TW/common-zh-TW.json
i18n/listeners/languageFiles/zh-TW/more-zh-TW.json
i18n/listeners/languageFiles/zh-TW/office-zh-TW.json
i18n/listeners/languageFiles/zh-TW/support-zh-TW.json
i18n/listeners/proxyContainer/AlertShouldBePresentProxy.py
i18n/listeners/proxyContainer/CountValuesInListProxy.py
i18n/listeners/proxyContainer/DictionariesShouldBeEqualProxy.py
i18n/listeners/proxyContainer/DictionaryShouldContainItemProxy.py
i18n/listeners/proxyContainer/DictionaryShouldContainKeyProxy.py
i18n/listeners/proxyContainer/DictionaryShouldContainValueProxy.py
i18n/listeners/proxyContainer/ElementTextShouldBeProxy.py
i18n/listeners/proxyContainer/FindElementsProxy.py
RF_i18n_tool-1.0.0.dist-info/LICENSE
RF_i18n_tool-1.0.0.dist-info/METADATA
RF_i18n_tool-1.0.0.dist-info/WHEEL
RF_i18n_tool-1.0.0.dist-info/top_level.txt
RF_i18n_tool-1.0.0.dist-info/RECORD
