Metadata-Version: 2.1
Name: RF-i18n-tool
Version: 1.0.0
Summary: i18n tool for RF web testing
Home-page: https://github.com/Rexmen/i18n.git
Author: Bing, James
Author-email: binchen561@gmail.com
License: UNKNOWN
Platform: UNKNOWN
Classifier: Programming Language :: Python :: 3
Classifier: License :: OSI Approved :: MIT License
Classifier: Operating System :: OS Independent
Requires-Python: >=3.6.0
License-File: LICENSE
